pastewin/__init__.py
pastewin/awyes_template.yml
pastewin/config.py
pastewin/pastewin.py
pastewin-1.0.8.dist-info/METADATA
pastewin-1.0.8.dist-info/WHEEL
pastewin-1.0.8.dist-info/entry_points.txt
pastewin-1.0.8.dist-info/top_level.txt
pastewin-1.0.8.dist-info/RECORD
