Metadata-Version: 2.1
Name: pastewin
Version: 1.0.8
Summary: A package to upload files to public s3 bucket
Home-page: https://github.com/bb-labs/pastewin
Author: Truman Purnell
Author-email: truman.purnell@gmail.com
Keywords: file public serve
Classifier: Development Status :: 3 - Alpha
Classifier: Intended Audience :: Developers
Classifier: License :: OSI Approved :: MIT License
Classifier: Programming Language :: Python :: 3
Classifier: Programming Language :: Python :: 3.6
Classifier: Programming Language :: Python :: 3.7
Classifier: Programming Language :: Python :: 3.8
Classifier: Programming Language :: Python :: 3.9
Requires-Dist: boto3
Requires-Dist: awyes
